start_django_project/__init__.py
start_django_project/cli.py
start_django_project/django-template/.env.dev.example
start_django_project/django-template/.env.prod.db.example
start_django_project/django-template/.env.prod.example
start_django_project/django-template/.pylintrc
start_django_project/django-template/.vscode/launch.json
start_django_project/django-template/.vscode/settings.json
start_django_project/django-template/.vscode/tasks.json
start_django_project/django-template/code/Dockerfile
start_django_project/django-template/code/Dockerfile.prod
start_django_project/django-template/code/manually_start.bat
start_django_project/django-template/code/requirements.txt
start_django_project/django-template/code/web/app/__init__.py
start_django_project/django-template/code/web/app/admin.py
start_django_project/django-template/code/web/app/api_router.py
start_django_project/django-template/code/web/app/api_views.py
start_django_project/django-template/code/web/app/apps.py
start_django_project/django-template/code/web/app/forms.py
start_django_project/django-template/code/web/app/management/commands/ensure_superuser.py
start_django_project/django-template/code/web/app/migrations/0001_initial.py
start_django_project/django-template/code/web/app/migrations/__init__.py
start_django_project/django-template/code/web/app/models.py
start_django_project/django-template/code/web/app/serializers.py
start_django_project/django-template/code/web/app/templates/app/about.html
start_django_project/django-template/code/web/app/templates/app/index.html
start_django_project/django-template/code/web/app/templates/app/login.html
start_django_project/django-template/code/web/app/templates/app/signup.html
start_django_project/django-template/code/web/app/templates/app/thanks.html
start_django_project/django-template/code/web/app/templates/base.html
start_django_project/django-template/code/web/app/tests.py
start_django_project/django-template/code/web/app/urls.py
start_django_project-2.1.0.dist-info/entry_points.txt
start_django_project-2.1.0.dist-info/LICENSE
start_django_project-2.1.0.dist-info/WHEEL
start_django_project-2.1.0.dist-info/METADATA
start_django_project-2.1.0.dist-info/RECORD
